jDocument/__init__.py
jDocument/helpers.py
jDocument/jDocument.py
jDocument/jsjson.py
jDocument-0.1.11.dist-info/LICENSE
jDocument-0.1.11.dist-info/METADATA
jDocument-0.1.11.dist-info/WHEEL
jDocument-0.1.11.dist-info/top_level.txt
jDocument-0.1.11.dist-info/RECORD
