Metadata-Version: 2.1
Name: jDocument
Version: 0.1.11
Summary: The jDocument class allows you to encapsulate a json document (dict or a list) and perform a lot of operations to read, update and add data.
Home-page: UNKNOWN
Author: Jose Cordeiro
License: MIT
Platform: UNKNOWN
License-File: LICENSE
